pyass/__init__.py
pyass/color.py
pyass/drawing.py
pyass/enum.py
pyass/event.py
pyass/float.py
pyass/position.py
pyass/script.py
pyass/section.py
pyass/style.py
pyass/tag.py
pyass/timedelta.py
pyass-0.1.4.dist-info/LICENSE
pyass-0.1.4.dist-info/METADATA
pyass-0.1.4.dist-info/WHEEL
pyass-0.1.4.dist-info/RECORD
